Sid/__init__.py
Sid/_version.py
Sid/take_cover.json
Sid/take_cover.py
Sid/images/__init__.py
Sid/images/image1.jpg
Sid/images/image2.jpg
Sid/images/image3.jpg
Sid/tests/__init__.py
Sid/tests/test_take_cover.py
Sid-0.2.5.dist-info/LICENCE.txt
Sid-0.2.5.dist-info/METADATA
Sid-0.2.5.dist-info/WHEEL
Sid-0.2.5.dist-info/entry_points.txt
Sid-0.2.5.dist-info/top_level.txt
Sid-0.2.5.dist-info/RECORD
